dbt/adapters/doris/__init__.py
dbt/adapters/doris/column.py
dbt/adapters/doris/connections.py
dbt/adapters/doris/impl.py
dbt/adapters/doris/relation.py
dbt/include/doris/__init__.py
dbt/include/doris/dbt_project.yml
dbt/include/doris/sample_profiles.yml
dbt/include/doris/macros/adapters/columns.sql
dbt/include/doris/macros/adapters/freshness.sql
dbt/include/doris/macros/adapters/metadata.sql
dbt/include/doris/macros/adapters/relation.sql
dbt/include/doris/macros/adapters/schema.sql
dbt/include/doris/macros/get_custom_name/get_custom_database.sql
dbt/include/doris/macros/materializations/incremental/is_incremental.sql
dbt/include/doris/macros/materializations/incremental/merge.sql
dbt/include/doris/macros/materializations/partition/helpers.sql
dbt/include/doris/macros/materializations/partition/partition.sql
dbt/include/doris/macros/materializations/partition/replace.sql
dbt/include/doris/macros/materializations/seed/helpers.sql
dbt/include/doris/macros/materializations/snapshot/snapshot.sql
dbt/include/doris/macros/materializations/snapshot/snapshot_merge.sql
dbt/include/doris/macros/materializations/snapshot/strategies.sql
dbt/include/doris/macros/materializations/table/create_table_as.sql
dbt/include/doris/macros/materializations/view/create_view_as.sql
dbt_doris_fp-0.1.1.dist-info/LICENSE
dbt_doris_fp-0.1.1.dist-info/METADATA
dbt_doris_fp-0.1.1.dist-info/WHEEL
dbt_doris_fp-0.1.1.dist-info/top_level.txt
dbt_doris_fp-0.1.1.dist-info/RECORD
